README.rst
setup.py
django_eros.egg-info/PKG-INFO
django_eros.egg-info/SOURCES.txt
django_eros.egg-info/dependency_links.txt
django_eros.egg-info/not-zip-safe
django_eros.egg-info/top_level.txt
eros/__init__.py
eros/base.py
eros/compat.py
eros/models.py
eros/registry.py
eros/settings.py
eros/urls.py
eros/util.py
eros/views.py
eros/management/__init__.py
eros/management/commands/__init__.py
eros/management/commands/sync_eros_cache.py
eros/tests/__init__.py
eros/tests/eros_registry.py
eros/tests/models.py
eros/tests/settings.py
eros/tests/test_models.py
eros/tests/test_views.py
eros/tests/urls.py